{ "height":15,
 "layers":[
        {
         "data":[1, 1, 1, 1, 1, 1, 1, 1, 1, 1, 1, 1, 1, 1, 1, 1, 1, 1, 1, 1, 1, 1, 1, 1, 1, 1, 1, 1, 1, 1, 15, 15, 15, 15, 15, 15, 15, 14, 1, 1, 1, 1, 1, 1, 1, 1, 4, 1, 1, 1, 1, 1, 14, 1, 1, 1, 1, 1, 1, 1, 1, 4, 3, 3, 3, 3, 3, 3, 1, 1, 1, 1, 1, 1, 1, 1, 1, 1, 1, 1, 1, 1, 1, 1, 1, 1, 1, 1, 1, 1, 2, 1, 1, 1, 1, 1, 1, 1, 1, 1, 1, 1, 1, 1, 1, 1, 1, 1, 1, 1, 1, 1, 1, 1, 1, 1, 1, 1, 1, 1, 1, 1, 1, 1, 1, 1, 1, 1, 1, 1, 1, 1, 1, 1, 1, 2, 2, 1, 1, 1, 1, 1, 1, 1, 1, 1, 1, 1, 1, 1, 1, 1, 1, 1, 1, 1, 1, 1, 1, 1, 1, 1, 1, 1, 1, 1, 1, 1, 1, 1, 1, 1, 1, 1, 1, 1, 1, 1, 1, 1, 1, 1, 1, 1, 1, 1, 1, 1, 1, 1, 1, 1, 1, 1, 1, 1, 1, 1, 1, 1, 1, 1, 1, 1, 1, 1, 1, 1, 1, 1, 1, 1, 1, 1, 1, 1, 1, 1, 1, 1, 1, 1, 1, 1, 1],
         "height":15,
         "name":"World1",
         "opacity":1,
         "properties":
            {
             "time":"1000"
            },
         "type":"tilelayer",
         "visible":true,
         "width":15,
         "x":0,
         "y":0
        }],
 "nextobjectid":1,
 "orientation":"orthogonal",
 "properties":
    {
     "mapProp":"123"
    },
 "renderorder":"right-down",
 "tileheight":32,
 "tilesets":[
        {
         "firstgid":1,
         "image":"super_mario.png",
         "imageheight":128,
         "imagewidth":352,
         "margin":0,
         "name":"SuperMarioBros-World1-1",
         "properties":
            {

            },
         "spacing":0,
         "tilecount":44,
         "tileheight":32,
         "tileproperties":
            {
             "13":
                {
                 "richtung":"down"
                },
             "14":
                {
                 "richtung":"right"
                },
             "2":
                {
                 "richtung":"left"
                },
             "3":
                {
                 "richtung":"up"
                }
            },
         "tilewidth":32
        }],
 "tilewidth":32,
 "version":1,
 "width":15
}